Patro/__init__.py
Patro/Common/ArgparseAction.py
Patro/Common/AtomicCounter.py
Patro/Common/Datetime.py
Patro/Common/IterTools.py
Patro/Common/Object.py
Patro/Common/Path.py
Patro/Common/Platform.py
Patro/Common/Singleton.py
Patro/Common/__init__.py
Patro/Common/Graph/DirectedAcyclicGraph.py
Patro/Common/Graph/__init__.py
Patro/Common/Logging/Logging.py
Patro/Common/Logging/__init__.py
Patro/Common/Math/Functions.py
Patro/Common/Math/Root.py
Patro/Common/Math/__init__.py
Patro/Common/Xml/Objectivity.py
Patro/Common/Xml/XmlFile.py
Patro/Common/Xml/__init__.py
Patro/Config/ConfigInstall.py
Patro/Config/__init__.py
Patro/Config/logging.yml
Patro/FileFormat/__init__.py
Patro/FileFormat/Dxf/Importer.py
Patro/FileFormat/Dxf/Polyline.py
Patro/FileFormat/Dxf/__init__.py
Patro/FileFormat/Svg/SvgFile.py
Patro/FileFormat/Svg/SvgFormat.py
Patro/FileFormat/Svg/__init__.py
Patro/FileFormat/Valentina/Measurement.py
Patro/FileFormat/Valentina/Pattern.py
Patro/FileFormat/Valentina/VitFormat.py
Patro/FileFormat/Valentina/__init__.py
Patro/GeometryEngine/Bezier.py
Patro/GeometryEngine/BoundingBox.py
Patro/GeometryEngine/Conic.py
Patro/GeometryEngine/Interpolation.py
Patro/GeometryEngine/Line.py
Patro/GeometryEngine/Mixin.py
Patro/GeometryEngine/Path.py
Patro/GeometryEngine/Polygon.py
Patro/GeometryEngine/Polyline.py
Patro/GeometryEngine/Primitive.py
Patro/GeometryEngine/Rectangle.py
Patro/GeometryEngine/Segment.py
Patro/GeometryEngine/Spline.py
Patro/GeometryEngine/Transformation.py
Patro/GeometryEngine/Triangle.py
Patro/GeometryEngine/Vector.py
Patro/GeometryEngine/__init__.py
Patro/GeometryEngine/Shape/ArrowHead.py
Patro/GeometryEngine/Shape/__init__.py
Patro/GraphicEngine/__init__.py
Patro/GraphicEngine/GraphicScene/GraphicItem.py
Patro/GraphicEngine/GraphicScene/GraphicItemMixin.py
Patro/GraphicEngine/GraphicScene/GraphicStyle.py
Patro/GraphicEngine/GraphicScene/Scene.py
Patro/GraphicEngine/GraphicScene/TypographyUnit.py
Patro/GraphicEngine/GraphicScene/__init__.py
Patro-0.3.0.dist-info/LICENSE-AGPL-3.0.md
Patro-0.3.0.dist-info/METADATA
Patro-0.3.0.dist-info/WHEEL
Patro-0.3.0.dist-info/top_level.txt
Patro-0.3.0.dist-info/RECORD
