Metadata-Version: 2.1
Name: Patro
Version: 0.3.0
Summary: A Python library to make pattern for fashion design
Home-page: https://github.com/FabriceSalvaire/Patro
Author: Fabrice Salvaire
Author-email: fabrice.salvaire@orange.fr
License: AGPLv3
Keywords: pattern making drafting digitising digitizing sewing fashion design garment cloth valentina seamly svg latex tikz geometry engine cad
Platform: any
Classifier: Topic :: Scientific/Engineering
Classifier: Development Status :: 4 - Beta
Classifier: License :: OSI Approved :: GNU General Public License v3 (GPLv3)
Classifier: Operating System :: OS Independent
Classifier: Programming Language :: Python :: 3.7
Requires-Dist: IntervalArithmetic
Requires-Dist: PyYAML
Requires-Dist: Rtree
Requires-Dist: astunparse
Requires-Dist: ezdxf
Requires-Dist: lxml
Requires-Dist: matplotlib
Requires-Dist: numpy
Requires-Dist: reportlab
Requires-Dist: sympy
